impulseest/__init__.py
impulseest/creation.py
impulseest/impulseest.py
impulseest-1.0.dist-info/LICENSE
impulseest-1.0.dist-info/METADATA
impulseest-1.0.dist-info/WHEEL
impulseest-1.0.dist-info/top_level.txt
impulseest-1.0.dist-info/RECORD
