Metadata-Version: 2.1
Name: impulseest
Version: 1.0
Summary: non-parametric impulse response estimation with input-output data
Home-page: https://github.com/LVF784/impulseest
Author: Luan V. Fiorio
Author-email: vfluan@gmail.com
License: UNKNOWN
Platform: UNKNOWN
Classifier: Programming Language :: Python :: 3
Classifier: License :: OSI Approved :: MIT License
Classifier: Operating System :: OS Independent
Requires-Python: >=3
